langrs/__init__.py
langrs/common.py
langrs/core.py
langrs/outlier_detection.py
langrs-1.1.2.dist-info/licenses/LICENSE
langrs-1.1.2.dist-info/METADATA
langrs-1.1.2.dist-info/WHEEL
langrs-1.1.2.dist-info/top_level.txt
langrs-1.1.2.dist-info/RECORD
