Metadata-Version: 2.4
Name: langrs
Version: 1.1.2
Summary: Remote sensing image segmentation using LangSAM
Home-page: https://github.com/MohanadDiab/langrs
Author: Mohanad Diab
Author-email: mdiab@eurac.edu
Classifier: Programming Language :: Python :: 3.10
Classifier: License :: OSI Approved :: MIT License
Classifier: Operating System :: OS Independent
Requires-Python: >=3.10
License-File: LICENSE
Requires-Dist: numpy
Requires-Dist: matplotlib
Requires-Dist: Pillow
Requires-Dist: rasterio
Requires-Dist: torch
Requires-Dist: scipy
Requires-Dist: scikit-learn
Requires-Dist: segment-geospatial
Requires-Dist: groundingdino-py
Dynamic: author
Dynamic: author-email
Dynamic: classifier
Dynamic: description
Dynamic: description-content-type
Dynamic: home-page
Dynamic: license-file
Dynamic: requires-dist
Dynamic: requires-python
Dynamic: summary
